README.md
setup.cfg
setup.py
examples/__init__.py
examples/b1.py
examples/c1.py
examples/cu1.py
examples/pdb1.py
examples/pdbwa1.py
examples/pdbwr1.py
examples/basic/__init__.py
examples/cuclass/__init__.py
examples/persistdb/__init__.py
examples/withadmin/__init__.py
examples/withroles/__init__.py
viauth/__init__.py
viauth/basic.py
viauth/userpriv.py
viauth.egg-info/PKG-INFO
viauth.egg-info/SOURCES.txt
viauth.egg-info/dependency_links.txt
viauth.egg-info/not-zip-safe
viauth.egg-info/requires.txt
viauth.egg-info/top_level.txt
viauth/persistdb/__init__.py
viauth/persistdb/adminarch.py
viauth/persistdb/withadmin.py
viauth/persistdb/withroles.py