Metadata-Version: 1.1
Name: viauth
Version: 0.2.2
Summary: vial-auth (viauth), a flask mini login/auth module for development bootstrapping
Home-page: https://github.com/toranova/viauth/
Author: Chia Jason
Author-email: chia_jason96@live.com
License: MIT
Download-URL: https://github.com/ToraNova/viauth/archive/refs/tags/v0.2.2.tar.gz
Keywords: Flask,Authentication
Platform: UNKNOWN
Classifier: Development Status :: 3 - Alpha
Classifier: Programming Language :: Python :: 3
Classifier: License :: OSI Approved :: MIT License
Classifier: Operating System :: OS Independent
Classifier: Intended Audience :: Developers
Classifier: License :: OSI Approved :: MIT License
Classifier: Programming Language :: Python :: 3
Classifier: Programming Language :: Python :: 3.6
Classifier: Programming Language :: Python :: 3.7
Classifier: Programming Language :: Python :: 3.8
